{"openapi":"3.1.0","info":{"title":"Chokepoints Read API","description":"Read-only access to canonical chokepoint data. Geometry is schematic. Redistribution-restricted (tainted) records are excluded by default.","version":"0.2.0"},"servers":[{"url":"/api"}],"paths":{"/health":{"get":{"summary":"Health","operationId":"health_health_get","responses":{"200":{"description":"Successful Response","content":{"application/json":{"schema":{"type":"object","title":"Response Health Health Get"}}}}}}},"/chokepoints":{"get":{"summary":"List Chokepoints","operationId":"list_chokepoints_chokepoints_get","security":[{"HTTPBearer":[]}],"parameters":[{"name":"family","in":"query","required":false,"schema":{"anyOf":[{"type":"string"},{"type":"null"}],"title":"Family"}},{"name":"priority_class","in":"query","required":false,"schema":{"anyOf":[{"enum":["P0","P1","P2","P3"],"type":"string"},{"type":"null"}],"title":"Priority Class"}},{"name":"macro_region","in":"query","required":false,"schema":{"anyOf":[{"type":"string"},{"type":"null"}],"title":"Macro Region"}},{"name":"include_tainted","in":"query","required":false,"schema":{"type":"boolean","default":false,"title":"Include Tainted"}},{"name":"limit","in":"query","required":false,"schema":{"type":"integer","maximum":500,"minimum":1,"default":100,"title":"Limit"}},{"name":"offset","in":"query","required":false,"schema":{"type":"integer","minimum":0,"default":0,"title":"Offset"}}],"responses":{"200":{"description":"Successful Response","content":{"application/json":{"schema":{"$ref":"#/components/schemas/ChokepointList"}}}},"422":{"description":"Validation Error","content":{"application/json":{"schema":{"$ref":"#/components/schemas/HTTPValidationError"}}}}}}},"/chokepoints/by-flow/{flow_type}":{"get":{"summary":"Chokepoints By Flow","operationId":"chokepoints_by_flow_chokepoints_by_flow__flow_type__get","security":[{"HTTPBearer":[]}],"parameters":[{"name":"flow_type","in":"path","required":true,"schema":{"type":"string","title":"Flow Type"}},{"name":"include_tainted","in":"query","required":false,"schema":{"type":"boolean","default":false,"title":"Include Tainted"}}],"responses":{"200":{"description":"Successful Response","content":{"application/json":{"schema":{"type":"array","items":{"$ref":"#/components/schemas/FlowChokepointOut"},"title":"Response Chokepoints By Flow Chokepoints By Flow  Flow Type  Get"}}}},"422":{"description":"Validation Error","content":{"application/json":{"schema":{"$ref":"#/components/schemas/HTTPValidationError"}}}}}}},"/chokepoints/by-risk/{risk_type}":{"get":{"summary":"Chokepoints By Risk","operationId":"chokepoints_by_risk_chokepoints_by_risk__risk_type__get","security":[{"HTTPBearer":[]}],"parameters":[{"name":"risk_type","in":"path","required":true,"schema":{"type":"string","title":"Risk Type"}},{"name":"include_tainted","in":"query","required":false,"schema":{"type":"boolean","default":false,"title":"Include Tainted"}}],"responses":{"200":{"description":"Successful Response","content":{"application/json":{"schema":{"type":"array","items":{"$ref":"#/components/schemas/RiskChokepointOut"},"title":"Response Chokepoints By Risk Chokepoints By Risk  Risk Type  Get"}}}},"422":{"description":"Validation Error","content":{"application/json":{"schema":{"$ref":"#/components/schemas/HTTPValidationError"}}}}}}},"/chokepoints/by-system/{system_id}":{"get":{"summary":"Chokepoints By System","operationId":"chokepoints_by_system_chokepoints_by_system__system_id__get","security":[{"HTTPBearer":[]}],"parameters":[{"name":"system_id","in":"path","required":true,"schema":{"type":"string","title":"System Id"}},{"name":"include_tainted","in":"query","required":false,"schema":{"type":"boolean","default":false,"title":"Include Tainted"}}],"responses":{"200":{"description":"Successful Response","content":{"application/json":{"schema":{"type":"array","items":{"$ref":"#/components/schemas/ChokepointSummary"},"title":"Response Chokepoints By System Chokepoints By System  System Id  Get"}}}},"422":{"description":"Validation Error","content":{"application/json":{"schema":{"$ref":"#/components/schemas/HTTPValidationError"}}}}}}},"/chokepoints/search":{"get":{"summary":"Search Chokepoints","operationId":"search_chokepoints_chokepoints_search_get","security":[{"HTTPBearer":[]}],"parameters":[{"name":"q","in":"query","required":true,"schema":{"type":"string","minLength":1,"maxLength":120,"title":"Q"}},{"name":"include_tainted","in":"query","required":false,"schema":{"type":"boolean","default":false,"title":"Include Tainted"}},{"name":"limit","in":"query","required":false,"schema":{"type":"integer","maximum":200,"minimum":1,"default":50,"title":"Limit"}}],"responses":{"200":{"description":"Successful Response","content":{"application/json":{"schema":{"$ref":"#/components/schemas/ChokepointList"}}}},"422":{"description":"Validation Error","content":{"application/json":{"schema":{"$ref":"#/components/schemas/HTTPValidationError"}}}}}}},"/chokepoints/nearby":{"get":{"summary":"Nearby Chokepoints","description":"Spatial proximity on the SCHEMATIC display_point — not navigational truth.","operationId":"nearby_chokepoints_chokepoints_nearby_get","security":[{"HTTPBearer":[]}],"parameters":[{"name":"lat","in":"query","required":true,"schema":{"type":"number","maximum":90.0,"minimum":-90.0,"title":"Lat"}},{"name":"lon","in":"query","required":true,"schema":{"type":"number","maximum":180.0,"minimum":-180.0,"title":"Lon"}},{"name":"radius_km","in":"query","required":false,"schema":{"type":"number","maximum":20000.0,"exclusiveMinimum":0.0,"default":500,"title":"Radius Km"}},{"name":"include_tainted","in":"query","required":false,"schema":{"type":"boolean","default":false,"title":"Include Tainted"}},{"name":"limit","in":"query","required":false,"schema":{"type":"integer","maximum":200,"minimum":1,"default":50,"title":"Limit"}}],"responses":{"200":{"description":"Successful Response","content":{"application/json":{"schema":{"$ref":"#/components/schemas/ChokepointList"}}}},"422":{"description":"Validation Error","content":{"application/json":{"schema":{"$ref":"#/components/schemas/HTTPValidationError"}}}}}}},"/chokepoints/{chokepoint_id}/perception-signals":{"get":{"summary":"Get Perception Signals","description":"Polymarket P3 perception signals for a chokepoint (ADR 0037) — anticipation, not evidence.\n\nThe source (`polymarket_gamma`) is uncleared (high license risk), so this endpoint is gated on\nthe `read_tainted` scope unconditionally; a plain `read` key gets 403.","operationId":"get_perception_signals_chokepoints__chokepoint_id__perception_signals_get","security":[{"HTTPBearer":[]}],"parameters":[{"name":"chokepoint_id","in":"path","required":true,"schema":{"type":"string","title":"Chokepoint Id"}},{"name":"limit","in":"query","required":false,"schema":{"type":"integer","maximum":500,"minimum":1,"default":200,"title":"Limit"}}],"responses":{"200":{"description":"Successful Response","content":{"application/json":{"schema":{"$ref":"#/components/schemas/PerceptionSignalList"}}}},"422":{"description":"Validation Error","content":{"application/json":{"schema":{"$ref":"#/components/schemas/HTTPValidationError"}}}}}}},"/chokepoints/{chokepoint_id}/fiche":{"get":{"summary":"Get Chokepoint Fiche","description":"Consolidated Chokepoint Control Method fiche as JSON (ADR 0049). Derived/candidate; validated\nanalytical readings only. There is intentionally NO global cross-chokepoint power ranking endpoint —\nleverage is grouped only within a leverage family for a single chokepoint.","operationId":"get_chokepoint_fiche_chokepoints__chokepoint_id__fiche_get","security":[{"HTTPBearer":[]}],"parameters":[{"name":"chokepoint_id","in":"path","required":true,"schema":{"type":"string","title":"Chokepoint Id"}},{"name":"include_tainted","in":"query","required":false,"schema":{"type":"boolean","default":false,"title":"Include Tainted"}}],"responses":{"200":{"description":"Successful Response","content":{"application/json":{"schema":{}}}},"422":{"description":"Validation Error","content":{"application/json":{"schema":{"$ref":"#/components/schemas/HTTPValidationError"}}}}}}},"/chokepoints/{chokepoint_id}/analysis":{"get":{"summary":"Get Chokepoint Engine Analysis","description":"Full typed output of EVERY analytical engine for this chokepoint (latest snapshot), plus its\nrelation edges and evidence claims. Derived/candidate, never canonical (ADR 0005). This is the JSON\ntwin of the detail page's \"Engine outputs\" section.","operationId":"get_chokepoint_engine_analysis_chokepoints__chokepoint_id__analysis_get","security":[{"HTTPBearer":[]}],"parameters":[{"name":"chokepoint_id","in":"path","required":true,"schema":{"type":"string","title":"Chokepoint Id"}},{"name":"include_tainted","in":"query","required":false,"schema":{"type":"boolean","default":false,"title":"Include Tainted"}}],"responses":{"200":{"description":"Successful Response","content":{"application/json":{"schema":{}}}},"422":{"description":"Validation Error","content":{"application/json":{"schema":{"$ref":"#/components/schemas/HTTPValidationError"}}}}}}},"/chokepoints/{chokepoint_id}/actors":{"get":{"summary":"Get Chokepoint Actors","description":"Validated actor↔chokepoint control edges for this object (canonical, ADR 0041/0043).","operationId":"get_chokepoint_actors_chokepoints__chokepoint_id__actors_get","security":[{"HTTPBearer":[]}],"parameters":[{"name":"chokepoint_id","in":"path","required":true,"schema":{"type":"string","title":"Chokepoint Id"}},{"name":"include_tainted","in":"query","required":false,"schema":{"type":"boolean","default":false,"title":"Include Tainted"}}],"responses":{"200":{"description":"Successful Response","content":{"application/json":{"schema":{"type":"array","items":{"$ref":"#/components/schemas/ActorControlOut"},"title":"Response Get Chokepoint Actors Chokepoints  Chokepoint Id  Actors Get"}}}},"422":{"description":"Validation Error","content":{"application/json":{"schema":{"$ref":"#/components/schemas/HTTPValidationError"}}}}}}},"/chokepoints/{chokepoint_id}/event-signals":{"get":{"summary":"Get Chokepoint Event Signals","description":"Raw append-only event-signal stream for this chokepoint (USGS hazards + GDELT media, ADR 0042).\nThe aggregated view is the event_pressure result in /chokepoints/{id}/analysis.","operationId":"get_chokepoint_event_signals_chokepoints__chokepoint_id__event_signals_get","security":[{"HTTPBearer":[]}],"parameters":[{"name":"chokepoint_id","in":"path","required":true,"schema":{"type":"string","title":"Chokepoint Id"}},{"name":"include_tainted","in":"query","required":false,"schema":{"type":"boolean","default":false,"title":"Include Tainted"}},{"name":"limit","in":"query","required":false,"schema":{"type":"integer","maximum":2000,"minimum":1,"default":500,"title":"Limit"}}],"responses":{"200":{"description":"Successful Response","content":{"application/json":{"schema":{"type":"array","items":{"$ref":"#/components/schemas/EventSignalOut"},"title":"Response Get Chokepoint Event Signals Chokepoints  Chokepoint Id  Event Signals Get"}}}},"422":{"description":"Validation Error","content":{"application/json":{"schema":{"$ref":"#/components/schemas/HTTPValidationError"}}}}}}},"/chokepoints/{chokepoint_id}":{"get":{"summary":"Get Chokepoint","operationId":"get_chokepoint_chokepoints__chokepoint_id__get","security":[{"HTTPBearer":[]}],"parameters":[{"name":"chokepoint_id","in":"path","required":true,"schema":{"type":"string","title":"Chokepoint Id"}},{"name":"include_tainted","in":"query","required":false,"schema":{"type":"boolean","default":false,"title":"Include Tainted"}}],"responses":{"200":{"description":"Successful Response","content":{"application/json":{"schema":{"$ref":"#/components/schemas/ChokepointDetail"}}}},"422":{"description":"Validation Error","content":{"application/json":{"schema":{"$ref":"#/components/schemas/HTTPValidationError"}}}}}}},"/sources":{"get":{"summary":"List Sources","operationId":"list_sources_sources_get","responses":{"200":{"description":"Successful Response","content":{"application/json":{"schema":{"items":{"$ref":"#/components/schemas/SourceOut"},"type":"array","title":"Response List Sources Sources Get"}}}}},"security":[{"HTTPBearer":[]}]}},"/relations":{"get":{"summary":"List Relations","operationId":"list_relations_relations_get","security":[{"HTTPBearer":[]}],"parameters":[{"name":"include_tainted","in":"query","required":false,"schema":{"type":"boolean","default":false,"title":"Include Tainted"}}],"responses":{"200":{"description":"Successful Response","content":{"application/json":{"schema":{"type":"array","items":{"$ref":"#/components/schemas/RelationOut"},"title":"Response List Relations Relations Get"}}}},"422":{"description":"Validation Error","content":{"application/json":{"schema":{"$ref":"#/components/schemas/HTTPValidationError"}}}}}}},"/actors":{"get":{"summary":"List Actors","description":"Validated actors and how many control edges each holds (canonical, ADR 0041/0043).","operationId":"list_actors_actors_get","responses":{"200":{"description":"Successful Response","content":{"application/json":{"schema":{"items":{"$ref":"#/components/schemas/ActorOut"},"type":"array","title":"Response List Actors Actors Get"}}}}},"security":[{"HTTPBearer":[]}]}},"/alerts":{"get":{"summary":"List Alerts","description":"Analytical alerts (ADR 0047). An alert is a trigger for review, not a conclusion. Live alerts\n(open/acknowledged) by default; pass review_status to filter. Tainted chokepoints are excluded\nunless include_tainted + scope.","operationId":"list_alerts_alerts_get","security":[{"HTTPBearer":[]}],"parameters":[{"name":"include_tainted","in":"query","required":false,"schema":{"type":"boolean","default":false,"title":"Include Tainted"}},{"name":"review_status","in":"query","required":false,"schema":{"anyOf":[{"type":"string"},{"type":"null"}],"description":"filter by review_status","title":"Review Status"},"description":"filter by review_status"},{"name":"chokepoint_id","in":"query","required":false,"schema":{"anyOf":[{"type":"string"},{"type":"null"}],"title":"Chokepoint Id"}},{"name":"limit","in":"query","required":false,"schema":{"type":"integer","maximum":2000,"minimum":1,"default":500,"title":"Limit"}}],"responses":{"200":{"description":"Successful Response","content":{"application/json":{"schema":{"type":"array","items":{"$ref":"#/components/schemas/AlertOut"},"title":"Response List Alerts Alerts Get"}}}},"422":{"description":"Validation Error","content":{"application/json":{"schema":{"$ref":"#/components/schemas/HTTPValidationError"}}}}}}},"/vocabularies":{"get":{"summary":"Get Vocabularies","description":"The controlled vocabularies behind the enum-enforced fields, including the CCM analytics lookups\n(control dimensions + family, actor profile types + criticality, alert types + default queue,\narchitecture labels). The single documented source of truth (schemas/vocabularies.py + DB).","operationId":"get_vocabularies_vocabularies_get","responses":{"200":{"description":"Successful Response","content":{"application/json":{"schema":{}}}}},"security":[{"HTTPBearer":[]}]}},"/strategic-systems":{"get":{"summary":"List Strategic Systems","operationId":"list_strategic_systems_strategic_systems_get","responses":{"200":{"description":"Successful Response","content":{"application/json":{"schema":{"items":{"$ref":"#/components/schemas/StrategicSystemOut"},"type":"array","title":"Response List Strategic Systems Strategic Systems Get"}}}}},"security":[{"HTTPBearer":[]}]}},"/strategic-systems/{system_id}":{"get":{"summary":"Get Strategic System","operationId":"get_strategic_system_strategic_systems__system_id__get","security":[{"HTTPBearer":[]}],"parameters":[{"name":"system_id","in":"path","required":true,"schema":{"type":"string","title":"System Id"}},{"name":"include_tainted","in":"query","required":false,"schema":{"type":"boolean","default":false,"title":"Include Tainted"}}],"responses":{"200":{"description":"Successful Response","content":{"application/json":{"schema":{"$ref":"#/components/schemas/StrategicSystemDetail"}}}},"422":{"description":"Validation Error","content":{"application/json":{"schema":{"$ref":"#/components/schemas/HTTPValidationError"}}}}}}},"/analytics/results":{"get":{"summary":"Analytics Results","description":"Read-only view of derived (candidate) analytical results. Taint-aware via the\nreferenced canonical object; results for non-chokepoint objects are not filtered.","operationId":"analytics_results_analytics_results_get","security":[{"HTTPBearer":[]}],"parameters":[{"name":"object_id","in":"query","required":false,"schema":{"anyOf":[{"type":"string"},{"type":"null"}],"title":"Object Id"}},{"name":"engine_id","in":"query","required":false,"schema":{"anyOf":[{"type":"string"},{"type":"null"}],"title":"Engine Id"}},{"name":"status","in":"query","required":false,"schema":{"anyOf":[{"type":"string"},{"type":"null"}],"title":"Status"}},{"name":"include_tainted","in":"query","required":false,"schema":{"type":"boolean","default":false,"title":"Include Tainted"}},{"name":"limit","in":"query","required":false,"schema":{"type":"integer","maximum":1000,"minimum":1,"default":200,"title":"Limit"}}],"responses":{"200":{"description":"Successful Response","content":{"application/json":{"schema":{"type":"array","items":{"$ref":"#/components/schemas/AnalyticalResultOut"},"title":"Response Analytics Results Analytics Results Get"}}}},"422":{"description":"Validation Error","content":{"application/json":{"schema":{"$ref":"#/components/schemas/HTTPValidationError"}}}}}}},"/analytics/engine-runs":{"get":{"summary":"Analytics Engine Runs","operationId":"analytics_engine_runs_analytics_engine_runs_get","security":[{"HTTPBearer":[]}],"parameters":[{"name":"engine_id","in":"query","required":false,"schema":{"anyOf":[{"type":"string"},{"type":"null"}],"title":"Engine Id"}}],"responses":{"200":{"description":"Successful Response","content":{"application/json":{"schema":{"type":"array","items":{"$ref":"#/components/schemas/EngineRunOut"},"title":"Response Analytics Engine Runs Analytics Engine Runs Get"}}}},"422":{"description":"Validation Error","content":{"application/json":{"schema":{"$ref":"#/components/schemas/HTTPValidationError"}}}}}}},"/episodes":{"get":{"summary":"List Episodes","operationId":"list_episodes_episodes_get","responses":{"200":{"description":"Successful Response","content":{"application/json":{"schema":{"items":{"$ref":"#/components/schemas/EpisodeOut"},"type":"array","title":"Response List Episodes Episodes Get"}}}}},"security":[{"HTTPBearer":[]}]}},"/episodes/{episode_key}":{"get":{"summary":"Get Episode","operationId":"get_episode_episodes__episode_key__get","security":[{"HTTPBearer":[]}],"parameters":[{"name":"episode_key","in":"path","required":true,"schema":{"type":"string","title":"Episode Key"}},{"name":"include_tainted","in":"query","required":false,"schema":{"type":"boolean","default":false,"title":"Include Tainted"}}],"responses":{"200":{"description":"Successful Response","content":{"application/json":{"schema":{"$ref":"#/components/schemas/EpisodeDetail"}}}},"422":{"description":"Validation Error","content":{"application/json":{"schema":{"$ref":"#/components/schemas/HTTPValidationError"}}}}}}},"/chokepoint-analyses":{"get":{"summary":"List Chokepoint Analyses","description":"Derived ToC + Leverage Points analyses available on disk (ADR 0027/0028).\n\nFile-backed (read-only Markdown), not canonical data — see ANALYSIS_DISCLAIMER.","operationId":"list_chokepoint_analyses_chokepoint_analyses_get","security":[{"HTTPBearer":[]}],"parameters":[{"name":"priority_class","in":"query","required":false,"schema":{"anyOf":[{"enum":["P0","P1","P2","P3"],"type":"string"},{"type":"null"}],"title":"Priority Class"}},{"name":"family","in":"query","required":false,"schema":{"anyOf":[{"type":"string"},{"type":"null"}],"title":"Family"}}],"responses":{"200":{"description":"Successful Response","content":{"application/json":{"schema":{"$ref":"#/components/schemas/ChokepointAnalysisList"}}}},"422":{"description":"Validation Error","content":{"application/json":{"schema":{"$ref":"#/components/schemas/HTTPValidationError"}}}}}}},"/chokepoint-analyses/{chokepoint_id}":{"get":{"summary":"Get Chokepoint Analysis","description":"Full derived analysis (synthesis + ToC + Leverage Points) for one chokepoint.","operationId":"get_chokepoint_analysis_chokepoint_analyses__chokepoint_id__get","security":[{"HTTPBearer":[]}],"parameters":[{"name":"chokepoint_id","in":"path","required":true,"schema":{"type":"string","title":"Chokepoint Id"}}],"responses":{"200":{"description":"Successful Response","content":{"application/json":{"schema":{"$ref":"#/components/schemas/ChokepointAnalysisDetail"}}}},"422":{"description":"Validation Error","content":{"application/json":{"schema":{"$ref":"#/components/schemas/HTTPValidationError"}}}}}}},"/chokepoint-analyses/{chokepoint_id}/{doc}":{"get":{"summary":"Get Chokepoint Analysis Doc","description":"Raw Markdown of one analysis doc (synthesis | theory-of-constraints | leverage-points).","operationId":"get_chokepoint_analysis_doc_chokepoint_analyses__chokepoint_id___doc__get","security":[{"HTTPBearer":[]}],"parameters":[{"name":"chokepoint_id","in":"path","required":true,"schema":{"type":"string","title":"Chokepoint Id"}},{"name":"doc","in":"path","required":true,"schema":{"type":"string","title":"Doc"}}],"responses":{"200":{"description":"Successful Response","content":{"text/plain":{"schema":{"type":"string"}}}},"422":{"description":"Validation Error","content":{"application/json":{"schema":{"$ref":"#/components/schemas/HTTPValidationError"}}}}}}},"/exports/geojson":{"get":{"summary":"Export Geojson","description":"FeatureCollection of schematic display/core geometry (same query as the explorer).","operationId":"export_geojson_exports_geojson_get","security":[{"HTTPBearer":[]}],"parameters":[{"name":"include_tainted","in":"query","required":false,"schema":{"type":"boolean","default":false,"title":"Include Tainted"}}],"responses":{"200":{"description":"Successful Response","content":{"application/json":{"schema":{}}}},"422":{"description":"Validation Error","content":{"application/json":{"schema":{"$ref":"#/components/schemas/HTTPValidationError"}}}}}}},"/exports/jsonl":{"get":{"summary":"Export Jsonl","description":"Stream one canonical chokepoint summary per line (JSON Lines).","operationId":"export_jsonl_exports_jsonl_get","security":[{"HTTPBearer":[]}],"parameters":[{"name":"include_tainted","in":"query","required":false,"schema":{"type":"boolean","default":false,"title":"Include Tainted"}}],"responses":{"200":{"description":"Successful Response","content":{"application/json":{"schema":{}}}},"422":{"description":"Validation Error","content":{"application/json":{"schema":{"$ref":"#/components/schemas/HTTPValidationError"}}}}}}}},"components":{"schemas":{"ActorControlOut":{"properties":{"actor_id":{"type":"string","title":"Actor Id"},"actor_name":{"anyOf":[{"type":"string"},{"type":"null"}],"title":"Actor Name"},"actor_type":{"anyOf":[{"type":"string"},{"type":"null"}],"title":"Actor Type"},"chokepoint_id":{"type":"string","title":"Chokepoint Id"},"control_type":{"type":"string","title":"Control Type"},"control_strength":{"anyOf":[{"type":"integer"},{"type":"null"}],"title":"Control Strength"},"basis":{"anyOf":[{"type":"string"},{"type":"null"}],"title":"Basis"},"source_confidence":{"anyOf":[{"type":"string"},{"type":"null"}],"title":"Source Confidence"},"valid_from":{"anyOf":[{"type":"string","format":"date"},{"type":"null"}],"title":"Valid From"},"valid_to":{"anyOf":[{"type":"string","format":"date"},{"type":"null"}],"title":"Valid To"}},"type":"object","required":["actor_id","chokepoint_id","control_type"],"title":"ActorControlOut"},"ActorOut":{"properties":{"id":{"type":"string","title":"Id"},"name":{"type":"string","title":"Name"},"actor_type":{"type":"string","title":"Actor Type"},"jurisdiction":{"anyOf":[{"type":"string"},{"type":"null"}],"title":"Jurisdiction"},"validation_status":{"type":"string","title":"Validation Status"},"control_edge_count":{"type":"integer","title":"Control Edge Count","default":0}},"type":"object","required":["id","name","actor_type","validation_status"],"title":"ActorOut"},"AlertOut":{"properties":{"id":{"type":"string","title":"Id"},"chokepoint_id":{"type":"string","title":"Chokepoint Id"},"canonical_name":{"anyOf":[{"type":"string"},{"type":"null"}],"title":"Canonical Name"},"alert_type":{"type":"string","title":"Alert Type"},"level":{"type":"string","title":"Level"},"time_horizon":{"type":"string","title":"Time Horizon"},"queue":{"type":"string","title":"Queue"},"trigger_summary":{"type":"string","title":"Trigger Summary"},"affected_dimensions":{"items":{"type":"string"},"type":"array","title":"Affected Dimensions","default":[]},"affected_actors":{"items":{"type":"string"},"type":"array","title":"Affected Actors","default":[]},"confidence":{"anyOf":[{"type":"string"},{"type":"null"}],"title":"Confidence"},"review_status":{"type":"string","title":"Review Status"},"generated_at":{"anyOf":[{"type":"string","format":"date-time"},{"type":"null"}],"title":"Generated At"},"disclaimer":{"type":"string","title":"Disclaimer","default":"Analytical results are derived, candidate outputs (not human-validated) and are never written back to canonical without a review gate."}},"type":"object","required":["id","chokepoint_id","alert_type","level","time_horizon","queue","trigger_summary","review_status"],"title":"AlertOut"},"AlternativeOut":{"properties":{"description":{"type":"string","title":"Description"},"target_object_id":{"anyOf":[{"type":"string"},{"type":"null"}],"title":"Target Object Id"},"affected_flows":{"items":{"type":"string"},"type":"array","title":"Affected Flows","default":[]},"cost_penalty":{"anyOf":[{"type":"string"},{"type":"null"}],"title":"Cost Penalty"},"time_penalty":{"anyOf":[{"type":"string"},{"type":"null"}],"title":"Time Penalty"},"capacity_penalty":{"anyOf":[{"type":"string"},{"type":"null"}],"title":"Capacity Penalty"},"feasibility":{"anyOf":[{"type":"string"},{"type":"null"}],"title":"Feasibility"},"substitution_note":{"anyOf":[{"type":"string"},{"type":"null"}],"title":"Substitution Note"},"validation_status":{"anyOf":[{"type":"string"},{"type":"null"}],"title":"Validation Status"},"reroute_deltas":{"items":{"$ref":"#/components/schemas/RerouteDeltaOut"},"type":"array","title":"Reroute Deltas","default":[]}},"type":"object","required":["description"],"title":"AlternativeOut"},"AnalyticalResultOut":{"properties":{"id":{"type":"string","title":"Id"},"run_id":{"type":"string","title":"Run Id"},"engine_id":{"type":"string","title":"Engine Id"},"engine_version":{"type":"string","title":"Engine Version"},"input_snapshot_id":{"type":"string","title":"Input Snapshot Id"},"object_id":{"type":"string","title":"Object Id"},"object_type":{"anyOf":[{"type":"string"},{"type":"null"}],"title":"Object Type"},"result_type":{"type":"string","title":"Result Type"},"status":{"type":"string","title":"Status"},"score":{"anyOf":[{"type":"number"},{"type":"null"}],"title":"Score"},"confidence":{"anyOf":[{"type":"string"},{"type":"null"}],"title":"Confidence"},"result_summary":{"anyOf":[{"type":"string"},{"type":"null"}],"title":"Result Summary"},"result_payload":{"anyOf":[{},{"type":"null"}],"title":"Result Payload"},"generated_at":{"anyOf":[{"type":"string","format":"date-time"},{"type":"null"}],"title":"Generated At"},"disclaimer":{"type":"string","title":"Disclaimer","default":"Analytical results are derived, candidate outputs (not human-validated) and are never written back to canonical without a review gate."}},"type":"object","required":["id","run_id","engine_id","engine_version","input_snapshot_id","object_id","result_type","status"],"title":"AnalyticalResultOut"},"ChokepointAnalysisDetail":{"properties":{"id":{"type":"string","title":"Id"},"canonical_name":{"type":"string","title":"Canonical Name"},"priority_class":{"type":"string","title":"Priority Class"},"family":{"type":"string","title":"Family"},"type":{"anyOf":[{"type":"string"},{"type":"null"}],"title":"Type"},"macro_region":{"anyOf":[{"type":"string"},{"type":"null"}],"title":"Macro Region"},"available_docs":{"items":{"type":"string"},"type":"array","title":"Available Docs","default":[]},"synthesis_md":{"anyOf":[{"type":"string"},{"type":"null"}],"title":"Synthesis Md"},"theory_of_constraints_md":{"anyOf":[{"type":"string"},{"type":"null"}],"title":"Theory Of Constraints Md"},"leverage_points_md":{"anyOf":[{"type":"string"},{"type":"null"}],"title":"Leverage Points Md"},"disclaimer":{"type":"string","title":"Disclaimer","default":"Derived systemic analysis (Theory of Constraints + Leverage Points, ADR 0027/0028). Figures are unvalidated public order-of-magnitude candidates pending human validation; capacities and geometry are schematic. No canonical mutation or priority promotion."}},"type":"object","required":["id","canonical_name","priority_class","family"],"title":"ChokepointAnalysisDetail"},"ChokepointAnalysisList":{"properties":{"count":{"type":"integer","title":"Count"},"items":{"items":{"$ref":"#/components/schemas/ChokepointAnalysisSummary"},"type":"array","title":"Items","default":[]},"disclaimer":{"type":"string","title":"Disclaimer","default":"Derived systemic analysis (Theory of Constraints + Leverage Points, ADR 0027/0028). Figures are unvalidated public order-of-magnitude candidates pending human validation; capacities and geometry are schematic. No canonical mutation or priority promotion."}},"type":"object","required":["count"],"title":"ChokepointAnalysisList"},"ChokepointAnalysisSummary":{"properties":{"id":{"type":"string","title":"Id"},"canonical_name":{"type":"string","title":"Canonical Name"},"priority_class":{"type":"string","title":"Priority Class"},"family":{"type":"string","title":"Family"},"type":{"anyOf":[{"type":"string"},{"type":"null"}],"title":"Type"},"macro_region":{"anyOf":[{"type":"string"},{"type":"null"}],"title":"Macro Region"},"available_docs":{"items":{"type":"string"},"type":"array","title":"Available Docs","default":[]}},"type":"object","required":["id","canonical_name","priority_class","family"],"title":"ChokepointAnalysisSummary","description":"One chokepoint's derived ToC + Leverage Points analysis (metadata only)."},"ChokepointDetail":{"properties":{"id":{"type":"string","title":"Id"},"canonical_name":{"type":"string","title":"Canonical Name"},"object_kind":{"type":"string","title":"Object Kind"},"family":{"type":"string","title":"Family"},"type":{"type":"string","title":"Type"},"priority_class":{"type":"string","title":"Priority Class"},"macro_region":{"anyOf":[{"type":"string"},{"type":"null"}],"title":"Macro Region"},"license_taint":{"type":"boolean","title":"License Taint"},"required_attributions":{"items":{"type":"string"},"type":"array","title":"Required Attributions","default":[]},"max_license_risk":{"anyOf":[{"type":"string"},{"type":"null"}],"title":"Max License Risk"},"flows":{"items":{"$ref":"#/components/schemas/FlowOut"},"type":"array","title":"Flows","default":[]},"risks":{"items":{"$ref":"#/components/schemas/RiskOut"},"type":"array","title":"Risks","default":[]},"geometries":{"items":{"$ref":"#/components/schemas/GeometryOut"},"type":"array","title":"Geometries","default":[]},"metrics":{"items":{"$ref":"#/components/schemas/MetricOut"},"type":"array","title":"Metrics","default":[]},"alternatives":{"items":{"$ref":"#/components/schemas/AlternativeOut"},"type":"array","title":"Alternatives","default":[]},"episodes":{"items":{"$ref":"#/components/schemas/ChokepointEpisodeOut"},"type":"array","title":"Episodes","default":[]},"source_ids":{"items":{"type":"string"},"type":"array","title":"Source Ids","default":[]},"geometry_disclaimer":{"type":"string","title":"Geometry Disclaimer","default":"Geometry is schematic and not validated for navigational or legal precision."}},"type":"object","required":["id","canonical_name","object_kind","family","type","priority_class","license_taint"],"title":"ChokepointDetail"},"ChokepointEpisodeOut":{"properties":{"episode_key":{"type":"string","title":"Episode Key"},"name":{"type":"string","title":"Name"},"started_on":{"anyOf":[{"type":"string","format":"date"},{"type":"null"}],"title":"Started On"},"ended_on":{"anyOf":[{"type":"string","format":"date"},{"type":"null"}],"title":"Ended On"},"status":{"type":"string","title":"Status"},"severity":{"anyOf":[{"type":"string"},{"type":"null"}],"title":"Severity"},"object_role":{"anyOf":[{"type":"string"},{"type":"null"}],"title":"Object Role"}},"type":"object","required":["episode_key","name","status"],"title":"ChokepointEpisodeOut","description":"A disruption episode as seen from one of its affected chokepoints."},"ChokepointList":{"properties":{"count":{"type":"integer","title":"Count"},"include_tainted":{"type":"boolean","title":"Include Tainted"},"attribution_notice":{"type":"string","title":"Attribution Notice","default":"Records may require source attribution. Redistribution-restricted (tainted) records are excluded by default; pass include_tainted=true to include them."},"items":{"items":{"$ref":"#/components/schemas/ChokepointSummary"},"type":"array","title":"Items","default":[]}},"type":"object","required":["count","include_tainted"],"title":"ChokepointList"},"ChokepointSummary":{"properties":{"id":{"type":"string","title":"Id"},"canonical_name":{"type":"string","title":"Canonical Name"},"object_kind":{"type":"string","title":"Object Kind"},"family":{"type":"string","title":"Family"},"type":{"type":"string","title":"Type"},"priority_class":{"type":"string","title":"Priority Class"},"macro_region":{"anyOf":[{"type":"string"},{"type":"null"}],"title":"Macro Region"},"license_taint":{"type":"boolean","title":"License Taint"},"required_attributions":{"items":{"type":"string"},"type":"array","title":"Required Attributions","default":[]},"max_license_risk":{"anyOf":[{"type":"string"},{"type":"null"}],"title":"Max License Risk"}},"type":"object","required":["id","canonical_name","object_kind","family","type","priority_class","license_taint"],"title":"ChokepointSummary"},"EngineRunOut":{"properties":{"run_id":{"type":"string","title":"Run Id"},"engine_id":{"type":"string","title":"Engine Id"},"engine_version":{"type":"string","title":"Engine Version"},"input_snapshot_id":{"type":"string","title":"Input Snapshot Id"},"status":{"type":"string","title":"Status"},"started_at":{"anyOf":[{"type":"string","format":"date-time"},{"type":"null"}],"title":"Started At"},"finished_at":{"anyOf":[{"type":"string","format":"date-time"},{"type":"null"}],"title":"Finished At"},"output_result_count":{"anyOf":[{"type":"integer"},{"type":"null"}],"title":"Output Result Count"},"error_message":{"anyOf":[{"type":"string"},{"type":"null"}],"title":"Error Message"}},"type":"object","required":["run_id","engine_id","engine_version","input_snapshot_id","status"],"title":"EngineRunOut"},"EpisodeDetail":{"properties":{"episode_key":{"type":"string","title":"Episode Key"},"name":{"type":"string","title":"Name"},"description":{"anyOf":[{"type":"string"},{"type":"null"}],"title":"Description"},"started_on":{"anyOf":[{"type":"string","format":"date"},{"type":"null"}],"title":"Started On"},"ended_on":{"anyOf":[{"type":"string","format":"date"},{"type":"null"}],"title":"Ended On"},"status":{"type":"string","title":"Status"},"severity":{"anyOf":[{"type":"string"},{"type":"null"}],"title":"Severity"},"affected_flows":{"items":{"type":"string"},"type":"array","title":"Affected Flows","default":[]},"object_count":{"type":"integer","title":"Object Count","default":0},"members":{"items":{"$ref":"#/components/schemas/EpisodeMemberOut"},"type":"array","title":"Members","default":[]}},"type":"object","required":["episode_key","name","status"],"title":"EpisodeDetail"},"EpisodeMemberOut":{"properties":{"chokepoint_id":{"type":"string","title":"Chokepoint Id"},"canonical_name":{"anyOf":[{"type":"string"},{"type":"null"}],"title":"Canonical Name"},"object_role":{"anyOf":[{"type":"string"},{"type":"null"}],"title":"Object Role"},"priority_class":{"anyOf":[{"type":"string"},{"type":"null"}],"title":"Priority Class"},"license_taint":{"type":"boolean","title":"License Taint","default":false}},"type":"object","required":["chokepoint_id"],"title":"EpisodeMemberOut"},"EpisodeOut":{"properties":{"episode_key":{"type":"string","title":"Episode Key"},"name":{"type":"string","title":"Name"},"description":{"anyOf":[{"type":"string"},{"type":"null"}],"title":"Description"},"started_on":{"anyOf":[{"type":"string","format":"date"},{"type":"null"}],"title":"Started On"},"ended_on":{"anyOf":[{"type":"string","format":"date"},{"type":"null"}],"title":"Ended On"},"status":{"type":"string","title":"Status"},"severity":{"anyOf":[{"type":"string"},{"type":"null"}],"title":"Severity"},"affected_flows":{"items":{"type":"string"},"type":"array","title":"Affected Flows","default":[]},"object_count":{"type":"integer","title":"Object Count","default":0}},"type":"object","required":["episode_key","name","status"],"title":"EpisodeOut"},"EventSignalOut":{"properties":{"chokepoint_id":{"type":"string","title":"Chokepoint Id"},"domain":{"type":"string","title":"Domain"},"weight":{"anyOf":[{"type":"number"},{"type":"null"}],"title":"Weight"},"observed_on":{"anyOf":[{"type":"string","format":"date"},{"type":"null"}],"title":"Observed On"},"event_key":{"anyOf":[{"type":"string"},{"type":"null"}],"title":"Event Key"}},"type":"object","required":["chokepoint_id","domain"],"title":"EventSignalOut"},"FlowChokepointOut":{"properties":{"id":{"type":"string","title":"Id"},"canonical_name":{"type":"string","title":"Canonical Name"},"object_kind":{"type":"string","title":"Object Kind"},"family":{"type":"string","title":"Family"},"type":{"type":"string","title":"Type"},"priority_class":{"type":"string","title":"Priority Class"},"macro_region":{"anyOf":[{"type":"string"},{"type":"null"}],"title":"Macro Region"},"license_taint":{"type":"boolean","title":"License Taint"},"required_attributions":{"items":{"type":"string"},"type":"array","title":"Required Attributions","default":[]},"max_license_risk":{"anyOf":[{"type":"string"},{"type":"null"}],"title":"Max License Risk"},"importance_score":{"anyOf":[{"type":"integer"},{"type":"null"}],"title":"Importance Score"}},"type":"object","required":["id","canonical_name","object_kind","family","type","priority_class","license_taint"],"title":"FlowChokepointOut","description":"A chokepoint matched by a given flow_type, carrying that flow's importance."},"FlowOut":{"properties":{"flow_type":{"type":"string","title":"Flow Type"},"importance_score":{"anyOf":[{"type":"integer"},{"type":"null"}],"title":"Importance Score"},"estimated_volume":{"anyOf":[{"type":"number"},{"type":"null"}],"title":"Estimated Volume"},"volume_unit":{"anyOf":[{"type":"string"},{"type":"null"}],"title":"Volume Unit"},"value_status":{"anyOf":[{"type":"string"},{"type":"null"}],"title":"Value Status"},"directionality":{"anyOf":[{"type":"string"},{"type":"null"}],"title":"Directionality"},"source_confidence":{"anyOf":[{"type":"string"},{"type":"null"}],"title":"Source Confidence"}},"type":"object","required":["flow_type"],"title":"FlowOut"},"GeometryOut":{"properties":{"geometry_role":{"type":"string","title":"Geometry Role"},"geometry_status":{"type":"string","title":"Geometry Status"},"geom_geojson":{"anyOf":[{},{"type":"null"}],"title":"Geom Geojson"}},"type":"object","required":["geometry_role","geometry_status"],"title":"GeometryOut"},"HTTPValidationError":{"properties":{"detail":{"items":{"$ref":"#/components/schemas/ValidationError"},"type":"array","title":"Detail"}},"type":"object","title":"HTTPValidationError"},"MetricOut":{"properties":{"metric_key":{"type":"string","title":"Metric Key"},"metric_label":{"anyOf":[{"type":"string"},{"type":"null"}],"title":"Metric Label"},"value":{"anyOf":[{"type":"number"},{"type":"null"}],"title":"Value"},"rank":{"anyOf":[{"type":"integer"},{"type":"null"}],"title":"Rank"},"unit":{"anyOf":[{"type":"string"},{"type":"null"}],"title":"Unit"},"period":{"anyOf":[{"type":"string"},{"type":"null"}],"title":"Period"},"source_id":{"anyOf":[{"type":"string"},{"type":"null"}],"title":"Source Id"},"url":{"anyOf":[{"type":"string"},{"type":"null"}],"title":"Url"}},"type":"object","required":["metric_key"],"title":"MetricOut"},"PerceptionConsensusOut":{"properties":{"signal_family":{"anyOf":[{"type":"string"},{"type":"null"}],"title":"Signal Family"},"market_count":{"anyOf":[{"type":"integer"},{"type":"null"}],"title":"Market Count"},"consensus_probability":{"anyOf":[{"type":"number"},{"type":"null"}],"title":"Consensus Probability"},"max_probability_change_24h":{"anyOf":[{"type":"number"},{"type":"null"}],"title":"Max Probability Change 24H"},"total_liquidity":{"anyOf":[{"type":"number"},{"type":"null"}],"title":"Total Liquidity"},"observed_window_end":{"anyOf":[{"type":"string","format":"date-time"},{"type":"null"}],"title":"Observed Window End"}},"type":"object","title":"PerceptionConsensusOut"},"PerceptionSignalList":{"properties":{"chokepoint_id":{"type":"string","title":"Chokepoint Id"},"count":{"type":"integer","title":"Count"},"consensus":{"items":{"$ref":"#/components/schemas/PerceptionConsensusOut"},"type":"array","title":"Consensus","default":[]},"signals":{"items":{"$ref":"#/components/schemas/PerceptionSignalOut"},"type":"array","title":"Signals","default":[]},"disclaimer":{"type":"string","title":"Disclaimer","default":"P3 perception signals from prediction markets (Polymarket, ADR 0037): crowd anticipation, NOT event evidence. The source is uncleared (high license risk); this endpoint requires the 'read_tainted' scope. Data never enters canonical without human validation."}},"type":"object","required":["chokepoint_id","count"],"title":"PerceptionSignalList"},"PerceptionSignalOut":{"properties":{"market_question":{"anyOf":[{"type":"string"},{"type":"null"}],"title":"Market Question"},"signal_family":{"anyOf":[{"type":"string"},{"type":"null"}],"title":"Signal Family"},"classification":{"anyOf":[{"type":"string"},{"type":"null"}],"title":"Classification"},"implied_probability":{"anyOf":[{"type":"number"},{"type":"null"}],"title":"Implied Probability"},"probability_change_24h":{"anyOf":[{"type":"number"},{"type":"null"}],"title":"Probability Change 24H"},"liquidity":{"anyOf":[{"type":"number"},{"type":"null"}],"title":"Liquidity"},"volume_24h":{"anyOf":[{"type":"number"},{"type":"null"}],"title":"Volume 24H"},"perception_signal_score":{"anyOf":[{"type":"integer"},{"type":"null"}],"title":"Perception Signal Score"},"proposed_action":{"anyOf":[{"type":"string"},{"type":"null"}],"title":"Proposed Action"},"observed_at":{"anyOf":[{"type":"string","format":"date-time"},{"type":"null"}],"title":"Observed At"}},"type":"object","title":"PerceptionSignalOut"},"RelationOut":{"properties":{"from_object_id":{"type":"string","title":"From Object Id"},"to_object_id":{"type":"string","title":"To Object Id"},"relation_type":{"type":"string","title":"Relation Type"},"directionality":{"type":"string","title":"Directionality"},"strength_score":{"anyOf":[{"type":"integer"},{"type":"null"}],"title":"Strength Score"},"analytical_effect":{"items":{"type":"string"},"type":"array","title":"Analytical Effect","default":[]},"affected_flows":{"items":{"type":"string"},"type":"array","title":"Affected Flows","default":[]}},"type":"object","required":["from_object_id","to_object_id","relation_type","directionality"],"title":"RelationOut"},"RerouteDeltaOut":{"properties":{"flow_type":{"type":"string","title":"Flow Type"},"vessel_class":{"anyOf":[{"type":"string"},{"type":"null"}],"title":"Vessel Class"},"delta_days":{"anyOf":[{"type":"number"},{"type":"null"}],"title":"Delta Days"},"delta_cost_usd":{"anyOf":[{"type":"number"},{"type":"null"}],"title":"Delta Cost Usd"},"toll_saved_usd":{"anyOf":[{"type":"number"},{"type":"null"}],"title":"Toll Saved Usd"},"net_cost_usd":{"anyOf":[{"type":"number"},{"type":"null"}],"title":"Net Cost Usd"},"suggested_cost_penalty":{"anyOf":[{"type":"string"},{"type":"null"}],"title":"Suggested Cost Penalty"},"corridor":{"anyOf":[{"type":"string"},{"type":"null"}],"title":"Corridor"}},"type":"object","required":["flow_type"],"title":"RerouteDeltaOut","description":"Per-flow reroute delta (searoute, schematic): added transit days + estimated added\nvoyage cost (bunkers ∝ distance + charter hire ∝ days), net of the canal toll the reroute\navoids (or incurs). The cost band is taken from net_cost_usd."},"RiskChokepointOut":{"properties":{"id":{"type":"string","title":"Id"},"canonical_name":{"type":"string","title":"Canonical Name"},"object_kind":{"type":"string","title":"Object Kind"},"family":{"type":"string","title":"Family"},"type":{"type":"string","title":"Type"},"priority_class":{"type":"string","title":"Priority Class"},"macro_region":{"anyOf":[{"type":"string"},{"type":"null"}],"title":"Macro Region"},"license_taint":{"type":"boolean","title":"License Taint"},"required_attributions":{"items":{"type":"string"},"type":"array","title":"Required Attributions","default":[]},"max_license_risk":{"anyOf":[{"type":"string"},{"type":"null"}],"title":"Max License Risk"},"impact_score":{"anyOf":[{"type":"integer"},{"type":"null"}],"title":"Impact Score"}},"type":"object","required":["id","canonical_name","object_kind","family","type","priority_class","license_taint"],"title":"RiskChokepointOut","description":"A chokepoint matched by a given risk_type, carrying that risk's impact."},"RiskOut":{"properties":{"risk_type":{"type":"string","title":"Risk Type"},"probability_score":{"anyOf":[{"type":"integer"},{"type":"null"}],"title":"Probability Score"},"impact_score":{"anyOf":[{"type":"integer"},{"type":"null"}],"title":"Impact Score"},"vulnerability_score":{"anyOf":[{"type":"integer"},{"type":"null"}],"title":"Vulnerability Score"},"current_status":{"anyOf":[{"type":"string"},{"type":"null"}],"title":"Current Status"},"triggers":{"items":{"type":"string"},"type":"array","title":"Triggers","default":[]},"affected_flows":{"items":{"type":"string"},"type":"array","title":"Affected Flows","default":[]}},"type":"object","required":["risk_type"],"title":"RiskOut"},"SourceOut":{"properties":{"source_id":{"type":"string","title":"Source Id"},"source_name":{"type":"string","title":"Source Name"},"source_level":{"type":"string","title":"Source Level"},"url":{"anyOf":[{"type":"string"},{"type":"null"}],"title":"Url"},"redistribution_allowed":{"anyOf":[{"type":"string"},{"type":"null"}],"title":"Redistribution Allowed"},"attribution_required":{"anyOf":[{"type":"boolean"},{"type":"null"}],"title":"Attribution Required"},"license_risk":{"anyOf":[{"type":"string"},{"type":"null"}],"title":"License Risk"},"domain_relevance":{"anyOf":[{},{"type":"null"}],"title":"Domain Relevance"},"evidence_types":{"items":{"type":"string"},"type":"array","title":"Evidence Types","default":[]},"storage_policy":{"anyOf":[{"type":"string"},{"type":"null"}],"title":"Storage Policy"}},"type":"object","required":["source_id","source_name","source_level"],"title":"SourceOut"},"StrategicSystemDetail":{"properties":{"id":{"type":"string","title":"Id"},"name":{"type":"string","title":"Name"},"system_type":{"type":"string","title":"System Type"},"priority_class":{"anyOf":[{"type":"string"},{"type":"null"}],"title":"Priority Class"},"notes":{"anyOf":[{"type":"string"},{"type":"null"}],"title":"Notes"},"member_count":{"type":"integer","title":"Member Count","default":0},"members":{"items":{"$ref":"#/components/schemas/SystemMemberOut"},"type":"array","title":"Members","default":[]}},"type":"object","required":["id","name","system_type"],"title":"StrategicSystemDetail"},"StrategicSystemOut":{"properties":{"id":{"type":"string","title":"Id"},"name":{"type":"string","title":"Name"},"system_type":{"type":"string","title":"System Type"},"priority_class":{"anyOf":[{"type":"string"},{"type":"null"}],"title":"Priority Class"},"notes":{"anyOf":[{"type":"string"},{"type":"null"}],"title":"Notes"},"member_count":{"type":"integer","title":"Member Count","default":0}},"type":"object","required":["id","name","system_type"],"title":"StrategicSystemOut"},"SystemMemberOut":{"properties":{"chokepoint_id":{"type":"string","title":"Chokepoint Id"},"canonical_name":{"anyOf":[{"type":"string"},{"type":"null"}],"title":"Canonical Name"},"member_role":{"anyOf":[{"type":"string"},{"type":"null"}],"title":"Member Role"},"priority_class":{"anyOf":[{"type":"string"},{"type":"null"}],"title":"Priority Class"},"license_taint":{"type":"boolean","title":"License Taint","default":false}},"type":"object","required":["chokepoint_id"],"title":"SystemMemberOut"},"ValidationError":{"properties":{"loc":{"items":{"anyOf":[{"type":"string"},{"type":"integer"}]},"type":"array","title":"Location"},"msg":{"type":"string","title":"Message"},"type":{"type":"string","title":"Error Type"}},"type":"object","required":["loc","msg","type"],"title":"ValidationError"}},"securitySchemes":{"HTTPBearer":{"type":"http","scheme":"bearer"}}}}